README.rst
setup.py
mease/__init__.py
mease/decorators.py
mease/fake.py
mease/messages.py
mease/permissions.py
mease/registry.py
mease/server.py
mease/tests.py
mease.egg-info/PKG-INFO
mease.egg-info/SOURCES.txt
mease.egg-info/dependency_links.txt
mease.egg-info/requires.txt
mease.egg-info/top_level.txt
mease/backends/__init__.py
mease/backends/base.py
mease/backends/rabbitmq.py
mease/backends/redis.py
mease/backends/test.py